tecton_parallel_retrieval/__init__.py
tecton_parallel_retrieval/model.py
tecton_parallel_retrieval/retrieval.py
tecton_parallel_retrieval/rift/__init__.py
tecton_parallel_retrieval/rift/retrieval.py
tecton_parallel_retrieval/rift/split.py
tecton_parallel_retrieval/spark/__init__.py
tecton_parallel_retrieval/spark/main.py
tecton_parallel_retrieval/spark/retrieval.py
tecton_parallel_retrieval/spark/split.py
tecton_parallel_retrieval-0.1.0.dist-info/METADATA
tecton_parallel_retrieval-0.1.0.dist-info/WHEEL
tecton_parallel_retrieval-0.1.0.dist-info/top_level.txt
tecton_parallel_retrieval-0.1.0.dist-info/RECORD
